create_docker_compose/__init__.py
create_docker_compose/create_docker_compose.py
create_env_file/__init__.py
create_env_file/create_env_file.py
create_docker_compose-0.3.dist-info/METADATA
create_docker_compose-0.3.dist-info/WHEEL
create_docker_compose-0.3.dist-info/entry_points.txt
create_docker_compose-0.3.dist-info/top_level.txt
create_docker_compose-0.3.dist-info/RECORD
