Metadata-Version: 2.1
Name: create-docker-compose
Version: 0.3
Requires-Dist: PyYAML
